pywemo/README.md
pywemo/__init__.py
pywemo/color.py
pywemo/discovery.py
pywemo/exceptions.py
pywemo/ouimeaux_device/LICENSE
pywemo/ouimeaux_device/__init__.py
pywemo/ouimeaux_device/api/__init__.py
pywemo/ouimeaux_device/api/attributes.py
pywemo/ouimeaux_device/api/db_orm.py
pywemo/ouimeaux_device/api/long_press.py
pywemo/ouimeaux_device/api/rules_db.py
pywemo/ouimeaux_device/api/service.py
pywemo/ouimeaux_device/api/wemo_services.py
pywemo/ouimeaux_device/api/wemo_services.pyi
pywemo/ouimeaux_device/api/xsd/__init__.py
pywemo/ouimeaux_device/api/xsd/device.py
pywemo/ouimeaux_device/api/xsd/device.xsd
pywemo/ouimeaux_device/api/xsd/service.py
pywemo/ouimeaux_device/api/xsd/service.xsd
pywemo/ouimeaux_device/api/xsd_types.py
pywemo/ouimeaux_device/bridge.py
pywemo/ouimeaux_device/coffeemaker.py
pywemo/ouimeaux_device/crockpot.py
pywemo/ouimeaux_device/dimmer.py
pywemo/ouimeaux_device/humidifier.py
pywemo/ouimeaux_device/insight.py
pywemo/ouimeaux_device/lightswitch.py
pywemo/ouimeaux_device/maker.py
pywemo/ouimeaux_device/motion.py
pywemo/ouimeaux_device/outdoor_plug.py
pywemo/ouimeaux_device/switch.py
pywemo/py.typed
pywemo/ssdp.py
pywemo/subscribe.py
pywemo/util.py
pywemo-2.0.0.dist-info/METADATA
pywemo-2.0.0.dist-info/WHEEL
pywemo-2.0.0.dist-info/licenses/LICENSE
pywemo-2.0.0.dist-info/RECORD
