Metadata-Version: 2.4
Name: pywemo
Version: 2.0.0
Summary: Lightweight Python module to discover and control WeMo devices
License: MIT
License-File: LICENSE
Keywords: wemo,api
Author: Eric Severance
Author-email: pywemo@esev.com
Requires-Python: >=3.10.0
Classifier: License :: OSI Approved :: MIT License
Classifier: Programming Language :: Python :: 3
Classifier: Programming Language :: Python :: 3.10
Classifier: Programming Language :: Python :: 3.11
Classifier: Programming Language :: Python :: 3.12
Classifier: Programming Language :: Python :: 3.13
Classifier: Programming Language :: Python :: 3.14
Requires-Dist: ifaddr (>=0.1.0)
Requires-Dist: lxml (>=4.6)
Requires-Dist: requests (>=2.0)
Requires-Dist: urllib3 (>=2.0.2)
Project-URL: Homepage, https://github.com/pywemo/pywemo
Project-URL: Repository, https://github.com/pywemo/pywemo
